pysacio/COPYING
pysacio/README
pysacio/__init__.py
pysacio/pysacio.py
pysacio/setup.py
pysacio-1.0.7.dist-info/licenses/COPYING
pysacio-1.0.7.dist-info/METADATA
pysacio-1.0.7.dist-info/WHEEL
pysacio-1.0.7.dist-info/top_level.txt
pysacio-1.0.7.dist-info/RECORD
