Metadata-Version: 2.4
Name: pysacio
Version: 1.0.7
Summary: Python module to read and write binary SAC (Seismic Analysis Code) files.
Home-page: 
License: 2-clause BSD
Classifier: License :: OSI Approved :: BSD License
Classifier: Programming Language :: Python :: 3
Classifier: Topic :: Scientific/Engineering :: Physics
License-File: COPYING
Requires-Dist: numpy>=2
Dynamic: classifier
Dynamic: description
Dynamic: description-content-type
Dynamic: license
Dynamic: license-file
Dynamic: requires-dist
Dynamic: summary
